[
{"link": "https://www.thesaddleryshop.co.uk/covid-19"},
{"link": "https://www.thesaddleryshop.co.uk/about-us"},
{"link": "https://www.thesaddleryshop.co.uk/returns"},
{"link": "https://www.thesaddleryshop.co.uk/delivery"},
{"link": "https://www.thesaddleryshop.co.uk/security"},
{"link": "https://www.thesaddleryshop.co.uk/contact-us"},
{"link": "https://www.thesaddleryshop.co.uk/blogs"},
{"link": "https://www.thesaddleryshop.co.uk/checkout"},
{"link": "https://www.thesaddleryshop.co.uk/members/wishlist"},
{"link": "https://www.thesaddleryshop.co.uk/members/login"},
{"link": "https://www.thesaddleryshop.co.uk/#level1"},
{"link": "https://www.thesaddleryshop.co.uk/"},
{"link": "https://www.thesaddleryshop.co.uk/members"},
{"link": "https://www.thesaddleryshop.co.uk/d_2_hoof-boots"},
{"link": "https://www.thesaddleryshop.co.uk/d_3_horse-stable"},
{"link": "https://www.thesaddleryshop.co.uk/d_6_horse-rugs"},
{"link": "https://www.thesaddleryshop.co.uk/d_1_horse-bits"},
{"link": "https://www.thesaddleryshop.co.uk/d_7_saddles-tack"},
{"link": "https://www.thesaddleryshop.co.uk/d_5_male-rider"},
{"link": "https://www.thesaddleryshop.co.uk/d_4_lady-rider"},
{"link": "https://www.thesaddleryshop.co.uk/d_8_young-rider"},
{"link": "https://www.thesaddleryshop.co.uk/d_1275_pet-products"},
{"link": "https://www.thesaddleryshop.co.uk/d_1299_christmas"},
{"link": "https://www.thesaddleryshop.co.uk/all-brands"},
{"link": "https://www.thesaddleryshop.co.uk/#level12"},
{"link": "https://www.thesaddleryshop.co.uk/#level31217"},
{"link": "https://www.thesaddleryshop.co.uk/c_1217_sale-easycare-hoof-boots"},
{"link": "https://www.thesaddleryshop.co.uk/sc_1218_all"},
{"link": "https://www.thesaddleryshop.co.uk/#level31187"},
{"link": "https://www.thesaddleryshop.co.uk/c_1187_hoof-boots-old-mac-hoof-boots"},
{"link": "https://www.thesaddleryshop.co.uk/sc_1266_new-mac-hoof-boots"},
{"link": "https://www.thesaddleryshop.co.uk/sc_360_hoof-boots-old-mac-hoof-boots-old-mac-g2-hoof-boots"},
{"link": "https://www.thesaddleryshop.co.uk/#level31186"},
{"link": "https://www.thesaddleryshop.co.uk/c_1186_hoof-boots-easycare-hoof-boots"},
{"link": "https://www.thesaddleryshop.co.uk/sc_1351_easyboot-sneaker-hoof-boot"},
{"link": "https://www.thesaddleryshop.co.uk/sc_1317_easyboot-fury-hoof-boot"},
{"link": "https://www.thesaddleryshop.co.uk/sc_1242_transition"},
{"link": "https://www.thesaddleryshop.co.uk/sc_355_hoof-boots-easycare-hoof-boots-glove"},
{"link": "https://www.thesaddleryshop.co.uk/sc_1268_new-trail-hoof-boots"},
{"link": "https://www.thesaddleryshop.co.uk/sc_1265_easyboot-cloud-therapy-hoof-boot"},
{"link": "https://www.thesaddleryshop.co.uk/sc_357_hoof-boots-easycare-hoof-boots-rx"},
{"link": "https://www.thesaddleryshop.co.uk/sc_351_hoof-boots-easycare-hoof-boots-easyboot-epic"},
{"link": "https://www.thesaddleryshop.co.uk/sc_422_hoof-boots-easycare-hoof-boots-easyboot-glove-back-country"},
{"link": "https://www.thesaddleryshop.co.uk/sc_350_hoof-boots-easycare-hoof-boots-easyboot"},
{"link": "https://www.thesaddleryshop.co.uk/sc_1306_easyboot-stratus-hoof-boot"},
{"link": "https://www.thesaddleryshop.co.uk/sc_361_hoof-boots-easycare-hoof-boots-glue"},
{"link": "https://www.thesaddleryshop.co.uk/sc_362_hoof-boots-easycare-hoof-boots-easycare-fit-kit"},
{"link": "https://www.thesaddleryshop.co.uk/#level31287"},
{"link": "https://www.thesaddleryshop.co.uk/c_1287_scoot-boots"},
{"link": "https://www.thesaddleryshop.co.uk/sc_1288_scoot-boots"},
{"link": "https://www.thesaddleryshop.co.uk/sc_1289_scoot-boots-fit-kit"},
{"link": "https://www.thesaddleryshop.co.uk/#level31194"},
{"link": "https://www.thesaddleryshop.co.uk/c_1194_hoof-boots-cavallo-hoof-boots"},
{"link": "https://www.thesaddleryshop.co.uk/sc_417_hoof-boots-cavallo-hoof-boots-cavallo-simple-and-sport-hoof-boots"},
{"link": "https://www.thesaddleryshop.co.uk/sc_418_hoof-boots-cavallo-hoof-boots-accessories-for-cavallo-hoof-boots"},
{"link": "https://www.thesaddleryshop.co.uk/#level31273"},
{"link": "https://www.thesaddleryshop.co.uk/c_1273_easyboot-mini-hoof-boots"},
{"link": "https://www.thesaddleryshop.co.uk/sc_1274_easycare-easyboot-mini-hoof-boot"},
{"link": "https://www.thesaddleryshop.co.uk/sc_1341_cavallo-cute-little-boot"},
{"link": "https://www.thesaddleryshop.co.uk/sc_1342_scoot-boot-mini"},
{"link": "https://www.thesaddleryshop.co.uk/#level31258"},
{"link": "https://www.thesaddleryshop.co.uk/c_1258_renegade-hoof-boots"},
{"link": "https://www.thesaddleryshop.co.uk/sc_1259_renegade-hoof-boots"},
{"link": "https://www.thesaddleryshop.co.uk/#level31285"},
{"link": "https://www.thesaddleryshop.co.uk/c_1285_evohorse-evo-hoof-boots-evo-boot"},
{"link": "https://www.thesaddleryshop.co.uk/sc_1286_evo-boot-10"},
{"link": "https://www.thesaddleryshop.co.uk/#level31249"},
{"link": "https://www.thesaddleryshop.co.uk/c_1249_equine-fusion-jogging-shoes"},
{"link": "https://www.thesaddleryshop.co.uk/sc_1250_equine-fusion-ultimate-jogging-shos"},
{"link": "https://www.thesaddleryshop.co.uk/#level31158"},
{"link": "https://www.thesaddleryshop.co.uk/c_1158_hoof-boots-hoof-boot-spares-accessories"},
{"link": "https://www.thesaddleryshop.co.uk/sc_1270_spares-suitable-for-new-mac-hoof-boots"},
{"link": "https://www.thesaddleryshop.co.uk/sc_1271_spares-suitable-for-new-trail-hoof-boots"},
{"link": "https://www.thesaddleryshop.co.uk/sc_208_hoof-boots-hoof-boot-spares-accessories-comfort-pads-inserts"},
{"link": "https://www.thesaddleryshop.co.uk/sc_209_hoof-boots-hoof-boot-spares-accessories-spares-suitable-for-the-easyboot-epic-bare-or-grip"},
{"link": "https://www.thesaddleryshop.co.uk/sc_210_hoof-boots-hoof-boot-spares-accessories-spares-suitable-for-the-boa-hoof-boot"},
{"link": "https://www.thesaddleryshop.co.uk/sc_211_hoof-boots-hoof-boot-spares-accessories-spares-suitable-for-old-macs-hoof-boots-g1-g2"},
{"link": "https://www.thesaddleryshop.co.uk/sc_212_hoof-boots-hoof-boot-spares-accessories-luggage-storage"},
{"link": "https://www.thesaddleryshop.co.uk/#level31159"},
{"link": "https://www.thesaddleryshop.co.uk/c_1159_hoof-boots-trimming-equipment"},
{"link": "https://www.thesaddleryshop.co.uk/sc_214_hoof-boots-trimming-equipment-all"},
{"link": "https://www.thesaddleryshop.co.uk/#level31304"},
{"link": "https://www.thesaddleryshop.co.uk/c_1304_easyboot-zip-hoof-boot"},
{"link": "https://www.thesaddleryshop.co.uk/sc_1305_easyboot-zip-hoof-boot"},
{"link": "https://www.thesaddleryshop.co.uk/#level3-2"},
{"link": "https://www.thesaddleryshop.co.uk/guides/intro"},
{"link": "https://www.thesaddleryshop.co.uk/enquiry-hoofboot"},
{"link": "https://www.thesaddleryshop.co.uk/barefoot-hoofboots-faq"},
{"link": "https://www.thesaddleryshop.co.uk/hoofboots-problems"},
{"link": "https://www.thesaddleryshop.co.uk/hoofboots-hiring"},
{"link": "https://www.thesaddleryshop.co.uk/measure-hoofboots"},
{"link": "https://www.thesaddleryshop.co.uk/hoof-size-charts"},
{"link": "https://www.thesaddleryshop.co.uk/#level13"},
{"link": "https://www.thesaddleryshop.co.uk/#level31149"},
{"link": "https://www.thesaddleryshop.co.uk/c_1149_horse-headcollars-ropes"},
{"link": "https://www.thesaddleryshop.co.uk/sc_337_horse-stable-headcollars-ropes-headcollar-leadrope-sets"},
{"link": "https://www.thesaddleryshop.co.uk/sc_415_horse-stable-headcollars-ropes-specialist-headcollars"},
{"link": "https://www.thesaddleryshop.co.uk/sc_416_horse-stable-headcollars-ropes-foal-headcollars-and-halters"},
{"link": "https://www.thesaddleryshop.co.uk/sc_145_horse-headcollars-ropes-headcollars"},
{"link": "https://www.thesaddleryshop.co.uk/sc_146_horse-headcollars-ropes-ropes-lead-reins"},
{"link": "https://www.thesaddleryshop.co.uk/#level31138"},
{"link": "https://www.thesaddleryshop.co.uk/c_1138_horse-horse-boots"},
{"link": "https://www.thesaddleryshop.co.uk/sc_372_horse-stable-horse-boots-bandages-leg-wraps"},
{"link": "https://www.thesaddleryshop.co.uk/sc_407_horse-stable-horse-boots-bandages-knee-boots"},
{"link": "https://www.thesaddleryshop.co.uk/sc_414_horse-stable-horse-boots-bandages-horse-therapy-boots-wraps-and-bandages"},
{"link": "https://www.thesaddleryshop.co.uk/sc_139_horse-horse-boots-bandages-brushing-boots"},
{"link": "https://www.thesaddleryshop.co.uk/sc_140_horse-horse-boots-bandages-tendon-fetlock-boots"},
{"link": "https://www.thesaddleryshop.co.uk/sc_141_horse-horse-boots-bandages-travelling-boots"},
{"link": "https://www.thesaddleryshop.co.uk/sc_142_horse-horse-boots-bandages-bandages-pads"},
{"link": "https://www.thesaddleryshop.co.uk/sc_143_horse-horse-boots-bandages-event-boots"},
{"link": "https://www.thesaddleryshop.co.uk/sc_144_horse-horse-boots-bandages-overreach-boots"},
{"link": "https://www.thesaddleryshop.co.uk/#level31136"},
{"link": "https://www.thesaddleryshop.co.uk/c_1136_horse-lunging"},
{"link": "https://www.thesaddleryshop.co.uk/sc_147_horse-lunging-rollers"},
{"link": "https://www.thesaddleryshop.co.uk/sc_148_horse-lunging-lunging-training-aids"},
{"link": "https://www.thesaddleryshop.co.uk/sc_149_horse-lunging-lunge-reins"},
{"link": "https://www.thesaddleryshop.co.uk/#level31146"},
{"link": "https://www.thesaddleryshop.co.uk/c_1146_horse-travelling-equipment"},
{"link": "https://www.thesaddleryshop.co.uk/sc_150_horse-travelling-equipment-travelling-boots"},
{"link": "https://www.thesaddleryshop.co.uk/sc_151_horse-travelling-equipment-bandages"},
{"link": "https://www.thesaddleryshop.co.uk/sc_152_horse-travelling-equipment-tail-guards"},
{"link": "https://www.thesaddleryshop.co.uk/sc_153_horse-travelling-equipment-poll-guards"},
{"link": "https://www.thesaddleryshop.co.uk/#level31141"},
{"link": "https://www.thesaddleryshop.co.uk/c_1141_horse-grooming-equipment"},
{"link": "https://www.thesaddleryshop.co.uk/sc_343_horse-stable-grooming-clippers-trimmers-clipper-blades"},
{"link": "https://www.thesaddleryshop.co.uk/sc_340_horse-stable-grooming-plaiting-bands-accessories"},
{"link": "https://www.thesaddleryshop.co.uk/sc_155_horse-grooming-complete-grooming-kits"},
{"link": "https://www.thesaddleryshop.co.uk/sc_156_horse-grooming-grooming-boxes-trays"},
{"link": "https://www.thesaddleryshop.co.uk/sc_157_horse-grooming-body-brushes"},
{"link": "https://www.thesaddleryshop.co.uk/sc_158_horse-grooming-dandy-brushes"},
{"link": "https://www.thesaddleryshop.co.uk/sc_159_horse-grooming-curry-combs"},
{"link": "https://www.thesaddleryshop.co.uk/sc_160_horse-stable-grooming-mane-tail-combs-brushes"},
{"link": "https://www.thesaddleryshop.co.uk/sc_163_horse-grooming-grooming-lotions"},
{"link": "https://www.thesaddleryshop.co.uk/sc_164_horse-grooming-shampoos"},
{"link": "https://www.thesaddleryshop.co.uk/sc_165_horse-grooming-sweat-scrapers"},
{"link": "https://www.thesaddleryshop.co.uk/sc_166_horse-grooming-other-grooming-essentials"},
{"link": "https://www.thesaddleryshop.co.uk/sc_167_horse-grooming-hoof-picks"},
{"link": "https://www.thesaddleryshop.co.uk/#level31144"},
{"link": "https://www.thesaddleryshop.co.uk/c_1144_horse-fly-protection"},
{"link": "https://www.thesaddleryshop.co.uk/sc_1345_fly-boots-and-uv-protection-for-horses"},
{"link": "https://www.thesaddleryshop.co.uk/sc_168_horse-fly-protection-fly-fringes"},
{"link": "https://www.thesaddleryshop.co.uk/sc_169_horse-fly-protection-fly-masks"},
{"link": "https://www.thesaddleryshop.co.uk/sc_170_horse-fly-protection-nose-nets"},
{"link": "https://www.thesaddleryshop.co.uk/sc_171_horse-stable-fly-protection-fly-repellent"},
{"link": "https://www.thesaddleryshop.co.uk/#level31145"},
{"link": "https://www.thesaddleryshop.co.uk/c_1145_horse-grazing-muzzles"},
{"link": "https://www.thesaddleryshop.co.uk/sc_174_horse-grazing-muzzles-nylon-grazing-muzzles"},
{"link": "https://www.thesaddleryshop.co.uk/#level31142"},
{"link": "https://www.thesaddleryshop.co.uk/c_1142_horse-stable-supplements-treats"},
{"link": "https://www.thesaddleryshop.co.uk/sc_322_horse-stable-supplements-treats-hoof-supplements"},
{"link": "https://www.thesaddleryshop.co.uk/sc_373_horse-stable-supplements-treats-general-vitamin-supplements"},
{"link": "https://www.thesaddleryshop.co.uk/sc_374_horse-stable-supplements-treats-equine-joint-supplements"},
{"link": "https://www.thesaddleryshop.co.uk/sc_375_horse-stable-supplements-treats-equine-breathing-supplements"},
{"link": "https://www.thesaddleryshop.co.uk/sc_381_horse-stable-supplements-treats-equine-calming-supplements"},
{"link": "https://www.thesaddleryshop.co.uk/sc_382_horse-stable-supplements-treats-hormonal-mare-supplements"},
{"link": "https://www.thesaddleryshop.co.uk/sc_383_horse-stable-supplements-treats-digestion-supplements"},
{"link": "https://www.thesaddleryshop.co.uk/sc_384_horse-stable-supplements-treats-natural-bute-substitutes"},
{"link": "https://www.thesaddleryshop.co.uk/sc_385_horse-stable-supplements-treats-seasonal-supplements-flies-sweet-itch-mud-fever-etc"},
{"link": "https://www.thesaddleryshop.co.uk/sc_386_horse-stable-supplements-treats-equine-immune-system-booster"},
{"link": "https://www.thesaddleryshop.co.uk/sc_388_horse-stable-supplements-treats-young-horse-spplements"},
{"link": "https://www.thesaddleryshop.co.uk/sc_390_horse-stable-supplements-treats-equine-appetisers-for-fussy-feeders"},
{"link": "https://www.thesaddleryshop.co.uk/sc_391_horse-stable-supplements-treats-equine-skin-supplements"},
{"link": "https://www.thesaddleryshop.co.uk/sc_393_horse-stable-supplements-treats-competition-horse-supplements"},
{"link": "https://www.thesaddleryshop.co.uk/sc_394_horse-stable-supplements-treats-electrolytes-for-horses"},
{"link": "https://www.thesaddleryshop.co.uk/sc_395_horse-stable-supplements-treats-other-supplements-for-horses"},
{"link": "https://www.thesaddleryshop.co.uk/sc_396_horse-stable-supplements-treats-weight-gain-or-energy-supplements-for-horses"},
{"link": "https://www.thesaddleryshop.co.uk/sc_397_horse-stable-supplements-treats-veteran-horse-supplements"},
{"link": "https://www.thesaddleryshop.co.uk/sc_176_horse-supplements-all"},
{"link": "https://www.thesaddleryshop.co.uk/#level31148"},
{"link": "https://www.thesaddleryshop.co.uk/c_1148_horse-road-safety"},
{"link": "https://www.thesaddleryshop.co.uk/sc_175_horse-road-safety-all"},
{"link": "https://www.thesaddleryshop.co.uk/#level31143"},
{"link": "https://www.thesaddleryshop.co.uk/c_1143_horse-stable-first-aid-topical-applications"},
{"link": "https://www.thesaddleryshop.co.uk/sc_421_horse-stable-first-aid-topical-applications-winter-horse-care"},
{"link": "https://www.thesaddleryshop.co.uk/sc_177_horse-first-aid-first-aid-equipment"},
{"link": "https://www.thesaddleryshop.co.uk/sc_178_horse-stable-first-aid-poultice-essentials"},
{"link": "https://www.thesaddleryshop.co.uk/sc_179_horse-stable-first-aid-equine-topical-applications"},
{"link": "https://www.thesaddleryshop.co.uk/#level31139"},
{"link": "https://www.thesaddleryshop.co.uk/c_1139_horse-stable-equipment"},
{"link": "https://www.thesaddleryshop.co.uk/sc_309_horse-stable-stable-field-equipment-miscellaneous"},
{"link": "https://www.thesaddleryshop.co.uk/sc_409_horse-stable-stable-field-equipment-electric-fencing"},
{"link": "https://www.thesaddleryshop.co.uk/sc_180_horse-stable-stable-field-equipment-haynets-hayracks"},
{"link": "https://www.thesaddleryshop.co.uk/sc_181_horse-stable-field-equipment-mucking-out-equipment"},
{"link": "https://www.thesaddleryshop.co.uk/sc_182_horse-stable-field-equipment-stable-toys"},
{"link": "https://www.thesaddleryshop.co.uk/sc_183_horse-stable-field-equipment-stable-tack-room-fittings"},
{"link": "https://www.thesaddleryshop.co.uk/sc_184_horse-stable-field-equipment-buckets"},
{"link": "https://www.thesaddleryshop.co.uk/#level31179"},
{"link": "https://www.thesaddleryshop.co.uk/c_1179_horse-stable-studs"},
{"link": "https://www.thesaddleryshop.co.uk/sc_332_horse-stable-studs-all"},
{"link": "https://www.thesaddleryshop.co.uk/#level31193"},
{"link": "https://www.thesaddleryshop.co.uk/c_1193_horse-stable-horsey-gifts-wrapping-paper-christmas-cards"},
{"link": "https://www.thesaddleryshop.co.uk/sc_368_horse-stable-christmas-gifts-equine-gifts"},
{"link": "https://www.thesaddleryshop.co.uk/sc_369_horse-stable-christmas-gifts-horsey-christmas-cards-and-horsey-gift-wrap"},
{"link": "https://www.thesaddleryshop.co.uk/#level31195"},
{"link": "https://www.thesaddleryshop.co.uk/c_1195_horse-stable-horse-therapy-magnetic-and-massage-products"},
{"link": "https://www.thesaddleryshop.co.uk/sc_419_horse-stable-horse-therapy-magnetic-and-massage-products-magnetic-horse-products"},
{"link": "https://www.thesaddleryshop.co.uk/sc_420_horse-stable-horse-therapy-magnetic-and-massage-products-horse-massage-therapy-products"},
{"link": "https://www.thesaddleryshop.co.uk/#level3-3"},
{"link": "https://www.thesaddleryshop.co.uk/#level16"},
{"link": "https://www.thesaddleryshop.co.uk/#level31163"},
{"link": "https://www.thesaddleryshop.co.uk/c_1163_rugs-turnout-rugs"},
{"link": "https://www.thesaddleryshop.co.uk/sc_263_rugs-turnout-rugs-lightweight-turnout-rugs"},
{"link": "https://www.thesaddleryshop.co.uk/sc_264_rugs-turnout-rugs-mediumweight-turnout-rugs"},
{"link": "https://www.thesaddleryshop.co.uk/sc_266_rugs-turnout-rugs-heavyweight-turnout-rugs"},
{"link": "https://www.thesaddleryshop.co.uk/sc_271_rugs-turnout-rugs-turnout-neck-covers"},
{"link": "https://www.thesaddleryshop.co.uk/#level31164"},
{"link": "https://www.thesaddleryshop.co.uk/c_1164_rugs-stable-rugs"},
{"link": "https://www.thesaddleryshop.co.uk/sc_268_rugs-stable-rugs-lightweight-stable-rugs"},
{"link": "https://www.thesaddleryshop.co.uk/sc_269_rugs-stable-rugs-mediumweight-stable-rugs"},
{"link": "https://www.thesaddleryshop.co.uk/sc_270_rugs-stable-rugs-heavyweight-stable-rugs"},
{"link": "https://www.thesaddleryshop.co.uk/sc_272_rugs-stable-rugs-stable-rug-neck-covers"},
{"link": "https://www.thesaddleryshop.co.uk/#level31166"},
{"link": "https://www.thesaddleryshop.co.uk/c_1166_rugs-under-rugs"},
{"link": "https://www.thesaddleryshop.co.uk/sc_280_rugs-under-rugs-all"},
{"link": "https://www.thesaddleryshop.co.uk/#level31261"},
{"link": "https://www.thesaddleryshop.co.uk/c_1261_horse-therapy-rugs"},
{"link": "https://www.thesaddleryshop.co.uk/sc_1262_horsevibe-massage-therapy-horse-rug"},
{"link": "https://www.thesaddleryshop.co.uk/sc_1264_ionic-therapy-products"},
{"link": "https://www.thesaddleryshop.co.uk/#level31168"},
{"link": "https://www.thesaddleryshop.co.uk/c_1168_rugs-fleece-cooler-rugs"},
{"link": "https://www.thesaddleryshop.co.uk/sc_273_rugs-fleece-cooler-rugs-fleece-rugs"},
{"link": "https://www.thesaddleryshop.co.uk/sc_274_rugs-fleece-cooler-rugs-cooler-rugs"},
{"link": "https://www.thesaddleryshop.co.uk/#level31167"},
{"link": "https://www.thesaddleryshop.co.uk/c_1167_rugs-summer-sheets"},
{"link": "https://www.thesaddleryshop.co.uk/sc_276_rugs-summer-sheets-all"},
{"link": "https://www.thesaddleryshop.co.uk/#level31165"},
{"link": "https://www.thesaddleryshop.co.uk/c_1165_rugs-fly-sun-protection-rugs"},
{"link": "https://www.thesaddleryshop.co.uk/sc_277_rugs-fly-sun-protection-rugs-all"},
{"link": "https://www.thesaddleryshop.co.uk/#level31169"},
{"link": "https://www.thesaddleryshop.co.uk/c_1169_rugs-foal-rugs"},
{"link": "https://www.thesaddleryshop.co.uk/sc_279_rugs-foal-rugs-all"},
{"link": "https://www.thesaddleryshop.co.uk/#level31170"},
{"link": "https://www.thesaddleryshop.co.uk/c_1170_rugs-excercise-rugs"},
{"link": "https://www.thesaddleryshop.co.uk/sc_281_rugs-excercise-rugs-waterproof-excercise-rugs"},
{"link": "https://www.thesaddleryshop.co.uk/sc_283_rugs-excercise-rugs-excercise-rugs"},
{"link": "https://www.thesaddleryshop.co.uk/#level31104"},
{"link": "https://www.thesaddleryshop.co.uk/c_1104_rugs-pony-rugs"},
{"link": "https://www.thesaddleryshop.co.uk/sc_284_rugs-rugs-especially-for-ponies-pony-turnout-rugs"},
{"link": "https://www.thesaddleryshop.co.uk/sc_285_rugs-rugs-especially-for-ponies-pony-stable-rugs"},
{"link": "https://www.thesaddleryshop.co.uk/sc_286_rugs-rugs-especially-for-ponies-pony-cooler-show-rugs"},
{"link": "https://www.thesaddleryshop.co.uk/sc_287_rugs-rugs-especially-for-ponies-pony-fly-sun-protection-rugs"},
{"link": "https://www.thesaddleryshop.co.uk/#level31172"},
{"link": "https://www.thesaddleryshop.co.uk/c_1172_rugs-anti-rub-vests-lycra-neck-covers"},
{"link": "https://www.thesaddleryshop.co.uk/sc_336_rugs-anti-rub-vests-all"},
{"link": "https://www.thesaddleryshop.co.uk/#level31171"},
{"link": "https://www.thesaddleryshop.co.uk/c_1171_rugs-rug-cleaning-reproofing"},
{"link": "https://www.thesaddleryshop.co.uk/sc_311_rugs-rug-cleaning-reproofing-spare-parts-rug-cleaning-and-rug-reproofing"},
{"link": "https://www.thesaddleryshop.co.uk/sc_399_rugs-rug-cleaning-reproofing-spare-parts-rug-sucingles-leg-straps-leg-straps-spares"},
{"link": "https://www.thesaddleryshop.co.uk/#level31189"},
{"link": "https://www.thesaddleryshop.co.uk/c_1189_rugs-clearance-rugs"},
{"link": "https://www.thesaddleryshop.co.uk/sc_363_rugs-clearance-rugs-all"},
{"link": "https://www.thesaddleryshop.co.uk/#level3-6"},
{"link": "https://www.thesaddleryshop.co.uk/guides-rugs/autumn-rugs"},
{"link": "https://www.thesaddleryshop.co.uk/horse-rugsizing-chart"},
{"link": "https://www.thesaddleryshop.co.uk/#level11"},
{"link": "https://www.thesaddleryshop.co.uk/#level31090"},
{"link": "https://www.thesaddleryshop.co.uk/c_1090_bits-myler-bits"},
{"link": "https://www.thesaddleryshop.co.uk/sc_325_bits-myler-bits-myler-hanging-cheek-bits"},
{"link": "https://www.thesaddleryshop.co.uk/sc_260_bits-myler-bits-eggbutt-with-hooks-30"},
{"link": "https://www.thesaddleryshop.co.uk/sc_261_bits-myler-bits-myler-pelhams-26"},
{"link": "https://www.thesaddleryshop.co.uk/#level31091"},
{"link": "https://www.thesaddleryshop.co.uk/c_1091_bits-sprenger-bits"},
{"link": "https://www.thesaddleryshop.co.uk/sc_1269_sprenger-novocontact-sensogan-bits"},
{"link": "https://www.thesaddleryshop.co.uk/sc_254_bits-sprenger-bits-sprenger-bradoons"},
{"link": "https://www.thesaddleryshop.co.uk/sc_255_bits-sprenger-bits-sprenger-wh-ultra-mouthpiece-bits"},
{"link": "https://www.thesaddleryshop.co.uk/sc_256_bits-sprenger-bits-sprenger-kk-ultra-mouthpiece-bits"},
{"link": "https://www.thesaddleryshop.co.uk/sc_257_bits-sprenger-bits-sprenger-rs-dynamic-mouthpiece-bits"},
{"link": "https://www.thesaddleryshop.co.uk/sc_258_bits-sprenger-bits-sprenger-turnado-bits"},
{"link": "https://www.thesaddleryshop.co.uk/sc_259_bits-sprenger-bits-diamond-paste"},
{"link": "https://www.thesaddleryshop.co.uk/#level31088"},
{"link": "https://www.thesaddleryshop.co.uk/c_1088_bits-korsteel-jp-bits"},
{"link": "https://www.thesaddleryshop.co.uk/sc_248_bits-korsteel-jp-bits-jp-snaffles"},
{"link": "https://www.thesaddleryshop.co.uk/sc_249_bits-korsteel-jp-bits-jp-continental-bits"},
{"link": "https://www.thesaddleryshop.co.uk/#level31073"},
{"link": "https://www.thesaddleryshop.co.uk/c_1073_bits-eggbutt-snaffles"},
{"link": "https://www.thesaddleryshop.co.uk/sc_315_bits-snaffle-bits-loop-ring-wilkie-snaffles"},
{"link": "https://www.thesaddleryshop.co.uk/sc_228_bits-snaffle-bits-loose-ring-snaffles"},
{"link": "https://www.thesaddleryshop.co.uk/sc_229_bits-snaffle-bits-eggbutt-snaffles"},
{"link": "https://www.thesaddleryshop.co.uk/sc_230_bits-snaffle-bits-full-cheek-snaffles"},
{"link": "https://www.thesaddleryshop.co.uk/sc_231_bits-snaffle-bits-d-cheek-snaffles"},
{"link": "https://www.thesaddleryshop.co.uk/sc_232_bits-snaffle-bits-fulmer-snaffles"},
{"link": "https://www.thesaddleryshop.co.uk/sc_237_bits-snaffle-bits-hanging-cheek-snaffles"},
{"link": "https://www.thesaddleryshop.co.uk/#level31077"},
{"link": "https://www.thesaddleryshop.co.uk/c_1077_bits-continental-bits"},
{"link": "https://www.thesaddleryshop.co.uk/sc_243_bits-continental-bits-3-ring-continental-bits"},
{"link": "https://www.thesaddleryshop.co.uk/sc_244_bits-continental-bits-4-ring-continental-bits"},
{"link": "https://www.thesaddleryshop.co.uk/#level31078"},
{"link": "https://www.thesaddleryshop.co.uk/c_1078_bits-pelhams"},
{"link": "https://www.thesaddleryshop.co.uk/sc_235_bits-pelhams-rugby-pelhams"},
{"link": "https://www.thesaddleryshop.co.uk/sc_236_bits-pelhams-pelhams"},
{"link": "https://www.thesaddleryshop.co.uk/#level31079"},
{"link": "https://www.thesaddleryshop.co.uk/c_1079_bits-kimblewick-bits"},
{"link": "https://www.thesaddleryshop.co.uk/sc_242_bits-kimblewick-bits-all"},
{"link": "https://www.thesaddleryshop.co.uk/#level31081"},
{"link": "https://www.thesaddleryshop.co.uk/c_1081_bits-gag-bits"},
{"link": "https://www.thesaddleryshop.co.uk/sc_329_bits-gag-bits-american-style-gag-bits"},
{"link": "https://www.thesaddleryshop.co.uk/sc_241_bits-gag-bits-traditional-gag-bits"},
{"link": "https://www.thesaddleryshop.co.uk/#level31083"},
{"link": "https://www.thesaddleryshop.co.uk/c_1083_bits-double-bridle-bits"},
{"link": "https://www.thesaddleryshop.co.uk/sc_233_bits-double-bridle-bits-weymouth-bits"},
{"link": "https://www.thesaddleryshop.co.uk/sc_234_bits-double-bridle-bits-bradoons"},
{"link": "https://www.thesaddleryshop.co.uk/#level31082"},
{"link": "https://www.thesaddleryshop.co.uk/c_1082_bits-hackamores"},
{"link": "https://www.thesaddleryshop.co.uk/sc_240_bits-hackamores-all"},
{"link": "https://www.thesaddleryshop.co.uk/#level31162"},
{"link": "https://www.thesaddleryshop.co.uk/c_1162_bits-in-hand-bits"},
{"link": "https://www.thesaddleryshop.co.uk/sc_239_bits-in-hand-bits-all"},
{"link": "https://www.thesaddleryshop.co.uk/#level31084"},
{"link": "https://www.thesaddleryshop.co.uk/c_1084_bits-driving-racing-bits"},
{"link": "https://www.thesaddleryshop.co.uk/sc_238_bits-driving-bits-all"},
{"link": "https://www.thesaddleryshop.co.uk/#level31094"},
{"link": "https://www.thesaddleryshop.co.uk/c_1094_bits-bit-accessories"},
{"link": "https://www.thesaddleryshop.co.uk/sc_278_bits-bit-accessories-all"},
{"link": "https://www.thesaddleryshop.co.uk/#level31085"},
{"link": "https://www.thesaddleryshop.co.uk/c_1085_bits-sweet-iron-copper-bits"},
{"link": "https://www.thesaddleryshop.co.uk/sc_1293_bits-sweet-iron-copper-bits-gag"},
{"link": "https://www.thesaddleryshop.co.uk/sc_245_bits-sweet-iron-copper-bits-snaffles"},
{"link": "https://www.thesaddleryshop.co.uk/sc_247_bits-sweet-iron-copper-bits-continental-bits"},
{"link": "https://www.thesaddleryshop.co.uk/#level31181"},
{"link": "https://www.thesaddleryshop.co.uk/c_1181_bits-neue-schule-bits"},
{"link": "https://www.thesaddleryshop.co.uk/sc_345_bits-neue-schule-bits-all"},
{"link": "https://www.thesaddleryshop.co.uk/#level3-1"},
{"link": "https://www.thesaddleryshop.co.uk/enquiry-bitting"},
{"link": "https://www.thesaddleryshop.co.uk/hiring-a-bit"},
{"link": "https://www.thesaddleryshop.co.uk/howto-choose-bits"},
{"link": "https://www.thesaddleryshop.co.uk/#level17"},
{"link": "https://www.thesaddleryshop.co.uk/#level31173"},
{"link": "https://www.thesaddleryshop.co.uk/c_1173_saddles-tack-saddle-gullets-spares"},
{"link": "https://www.thesaddleryshop.co.uk/sc_289_saddles-tack-saddle-gullets-spares-gullets-for-wintec-bates-saddles"},
{"link": "https://www.thesaddleryshop.co.uk/sc_1239_wintec-riser-system"},
{"link": "https://www.thesaddleryshop.co.uk/#level31161"},
{"link": "https://www.thesaddleryshop.co.uk/c_1161_saddles-tack-stirrup-leathers-stirrup-straps"},
{"link": "https://www.thesaddleryshop.co.uk/sc_225_saddles-tack-stirrup-leathers-stirrup-straps-stirrup-leathers"},
{"link": "https://www.thesaddleryshop.co.uk/sc_227_saddles-tack-stirrup-leathers-stirrup-straps-synthetic-stirrup-straps-leathers"},
{"link": "https://www.thesaddleryshop.co.uk/#level31133"},
{"link": "https://www.thesaddleryshop.co.uk/c_1133_saddles-tack-stirrups-treads"},
{"link": "https://www.thesaddleryshop.co.uk/sc_330_saddles-tack-stirrups-treads-stirrup-treads"},
{"link": "https://www.thesaddleryshop.co.uk/sc_194_saddles-tack-stirrups-treads-stirrups"},
{"link": "https://www.thesaddleryshop.co.uk/#level31131"},
{"link": "https://www.thesaddleryshop.co.uk/c_1131_saddles-under-the-saddle"},
{"link": "https://www.thesaddleryshop.co.uk/sc_1296_endurance-saddlecloths-and-numnahs"},
{"link": "https://www.thesaddleryshop.co.uk/sc_1297_working-hunter-numnahs-saddlecloths"},
{"link": "https://www.thesaddleryshop.co.uk/sc_1257_gel-pads"},
{"link": "https://www.thesaddleryshop.co.uk/sc_403_saddles-tack-under-the-saddle-dressage-numnahs"},
{"link": "https://www.thesaddleryshop.co.uk/sc_404_saddles-tack-under-the-saddle-dressage-numnahs"},
{"link": "https://www.thesaddleryshop.co.uk/sc_405_saddles-tack-under-the-saddle-jumping-close-contact-saddle-numnahs-saddlecloths"},
{"link": "https://www.thesaddleryshop.co.uk/sc_204_saddles-under-the-saddle-numnahs"},
{"link": "https://www.thesaddleryshop.co.uk/sc_205_saddles-under-the-saddle-saddlecloths"},
{"link": "https://www.thesaddleryshop.co.uk/sc_206_saddles-under-the-saddle-12-pads"},
{"link": "https://www.thesaddleryshop.co.uk/sc_207_saddles-under-the-saddle-riser-pads"},
{"link": "https://www.thesaddleryshop.co.uk/#level31132"},
{"link": "https://www.thesaddleryshop.co.uk/c_1132_saddles-girths"},
{"link": "https://www.thesaddleryshop.co.uk/sc_400_saddles-tack-girths-stud-girths"},
{"link": "https://www.thesaddleryshop.co.uk/sc_189_saddles-girths-dressage-girths"},
{"link": "https://www.thesaddleryshop.co.uk/sc_192_saddles-girths-gp-girths"},
{"link": "https://www.thesaddleryshop.co.uk/sc_200_saddles-girths-girth-sleeves"},
{"link": "https://www.thesaddleryshop.co.uk/#level31147"},
{"link": "https://www.thesaddleryshop.co.uk/c_1147_saddles-seat-savers"},
{"link": "https://www.thesaddleryshop.co.uk/sc_201_saddles-seat-savers-all"},
{"link": "https://www.thesaddleryshop.co.uk/#level31125"},
{"link": "https://www.thesaddleryshop.co.uk/c_1125_saddles-bridles"},
{"link": "https://www.thesaddleryshop.co.uk/sc_1252_inhand-bridles"},
{"link": "https://www.thesaddleryshop.co.uk/sc_1313_micklem-competition-multi-bridle"},
{"link": "https://www.thesaddleryshop.co.uk/sc_312_saddles-tack-bridles-double-bridles"},
{"link": "https://www.thesaddleryshop.co.uk/sc_370_saddles-tack-bridles-bitless-bridles"},
{"link": "https://www.thesaddleryshop.co.uk/sc_195_saddles-bridles-flash-bridles"},
{"link": "https://www.thesaddleryshop.co.uk/sc_196_saddles-bridles-raised-cavesson-bridles"},
{"link": "https://www.thesaddleryshop.co.uk/sc_198_saddles-bridles-grackle-bridles"},
{"link": "https://www.thesaddleryshop.co.uk/#level31129"},
{"link": "https://www.thesaddleryshop.co.uk/c_1129_saddles-bridle-spares"},
{"link": "https://www.thesaddleryshop.co.uk/sc_313_saddles-tack-bridle-spares-head-pieces-and-cheek-pieces"},
{"link": "https://www.thesaddleryshop.co.uk/sc_314_saddles-tack-bridle-spares-flash-straps-flash-converters"},
{"link": "https://www.thesaddleryshop.co.uk/sc_401_saddles-tack-bridle-spares-browbands"},
{"link": "https://www.thesaddleryshop.co.uk/sc_402_saddles-tack-bridle-spares-nosebands"},
{"link": "https://www.thesaddleryshop.co.uk/sc_199_saddles-bridle-spares-reins"},
{"link": "https://www.thesaddleryshop.co.uk/#level31126"},
{"link": "https://www.thesaddleryshop.co.uk/c_1126_lady-rider-martingales-breastplates"},
{"link": "https://www.thesaddleryshop.co.uk/sc_185_saddles-martingales-breastplates-running-martingales"},
{"link": "https://www.thesaddleryshop.co.uk/sc_186_saddles-martingales-breastplates-standing-martingales"},
{"link": "https://www.thesaddleryshop.co.uk/sc_188_saddles-martingales-breastplates-breastplates"},
{"link": "https://www.thesaddleryshop.co.uk/#level31128"},
{"link": "https://www.thesaddleryshop.co.uk/c_1128_saddles-training-aids"},
{"link": "https://www.thesaddleryshop.co.uk/sc_193_saddles-training-aids-all"},
{"link": "https://www.thesaddleryshop.co.uk/#level31130"},
{"link": "https://www.thesaddleryshop.co.uk/c_1130_saddles-tack-saddle-care"},
{"link": "https://www.thesaddleryshop.co.uk/sc_310_saddles-tack-tack-saddle-care-tack-care-accessories"},
{"link": "https://www.thesaddleryshop.co.uk/sc_202_saddles-tack-saddle-care-leather-cleaners"},
{"link": "https://www.thesaddleryshop.co.uk/sc_203_saddles-tack-saddle-care-leather-feed-condtioners"},
{"link": "https://www.thesaddleryshop.co.uk/sc_288_saddles-tack-tack-saddle-care-synthetic-saddle-tack-cleaner"},
{"link": "https://www.thesaddleryshop.co.uk/#level31135"},
{"link": "https://www.thesaddleryshop.co.uk/c_1135_saddles-accessories"},
{"link": "https://www.thesaddleryshop.co.uk/sc_307_saddles-tack-accessories-tack-luggage"},
{"link": "https://www.thesaddleryshop.co.uk/sc_371_saddles-tack-accessories-other-accessories"},
{"link": "https://www.thesaddleryshop.co.uk/sc_408_saddles-tack-accessories-saddle-covers"},
{"link": "https://www.thesaddleryshop.co.uk/#level31123"},
{"link": "https://www.thesaddleryshop.co.uk/c_1123_saddles-saddles-sorted-by-style"},
{"link": "https://www.thesaddleryshop.co.uk/sc_290_saddles-tack-saddles-sorted-by-style-general-purpose-saddles"},
{"link": "https://www.thesaddleryshop.co.uk/sc_293_saddles-tack-saddles-sorted-by-style-pony-saddles"},
{"link": "https://www.thesaddleryshop.co.uk/#level31339"},
{"link": "https://www.thesaddleryshop.co.uk/c_1339_fly-and-noise-reducing-ear-nets"},
{"link": "https://www.thesaddleryshop.co.uk/sc_1340_fly-and-noise-reducing-ear-nets"},
{"link": "https://www.thesaddleryshop.co.uk/#level3-7"},
{"link": "https://www.thesaddleryshop.co.uk/wintec-saddles-intro"},
{"link": "https://www.thesaddleryshop.co.uk/#level15"},
{"link": "https://www.thesaddleryshop.co.uk/#level31322"},
{"link": "https://www.thesaddleryshop.co.uk/c_1322_mens-clearance-riding-clothing"},
{"link": "https://www.thesaddleryshop.co.uk/sc_1344_mens-clearance-riding-clothing"},
{"link": "https://www.thesaddleryshop.co.uk/#level31107"},
{"link": "https://www.thesaddleryshop.co.uk/c_1107_male-rider-jodhpurs-breeches"},
{"link": "https://www.thesaddleryshop.co.uk/sc_110_male-rider-jodhpurs-breeches-jodhpurs-breeches"},
{"link": "https://www.thesaddleryshop.co.uk/sc_1316_breeches"},
{"link": "https://www.thesaddleryshop.co.uk/sc_111_male-rider-jodhpurs-breeches-other-riding-legwear"},
{"link": "https://www.thesaddleryshop.co.uk/#level31111"},
{"link": "https://www.thesaddleryshop.co.uk/c_1111_male-rider-casual-riding-clothing"},
{"link": "https://www.thesaddleryshop.co.uk/sc_120_male-rider-casual-riding-clothing-mens-riding-gloves"},
{"link": "https://www.thesaddleryshop.co.uk/sc_297_male-rider-casual-riding-clothing-mens-riding-socks"},
{"link": "https://www.thesaddleryshop.co.uk/sc_1327_mens-caps-hats"},
{"link": "https://www.thesaddleryshop.co.uk/sc_137_male-rider-casual-riding-clothing-high-visibility"},
{"link": "https://www.thesaddleryshop.co.uk/sc_1326_mens-base-layers-underwear"},
{"link": "https://www.thesaddleryshop.co.uk/sc_122_male-rider-casual-riding-clothing-mens-riding-shirts-tops"},
{"link": "https://www.thesaddleryshop.co.uk/sc_1325_mens-fleece-jackets-jumpers-hoodies"},
{"link": "https://www.thesaddleryshop.co.uk/sc_1324_mens-waistcoats-gilets"},
{"link": "https://www.thesaddleryshop.co.uk/sc_119_male-rider-casual-riding-clothing-mens-riding-jackets"},
{"link": "https://www.thesaddleryshop.co.uk/#level31110"},
{"link": "https://www.thesaddleryshop.co.uk/c_1110_male-rider-footwear"},
{"link": "https://www.thesaddleryshop.co.uk/sc_1328_mens-country-boots"},
{"link": "https://www.thesaddleryshop.co.uk/sc_1329_mens-long-leather-riding-boots"},
{"link": "https://www.thesaddleryshop.co.uk/sc_1330_mens-long-synthetic-riding-boots"},
{"link": "https://www.thesaddleryshop.co.uk/sc_116_male-rider-footwear-mens-riding-boots"},
{"link": "https://www.thesaddleryshop.co.uk/sc_118_male-rider-footwear-mens-yard-boots"},
{"link": "https://www.thesaddleryshop.co.uk/sc_1331_mens-long-yard-boots"},
{"link": "https://www.thesaddleryshop.co.uk/sc_306_male-rider-footwear-mens-wellington-boots"},
{"link": "https://www.thesaddleryshop.co.uk/sc_319_male-rider-footwear-accessories"},
{"link": "https://www.thesaddleryshop.co.uk/sc_300_male-rider-footwear-mens-riding-socks"},
{"link": "https://www.thesaddleryshop.co.uk/#level31106"},
{"link": "https://www.thesaddleryshop.co.uk/c_1106_male-rider-riding-hats"},
{"link": "https://www.thesaddleryshop.co.uk/sc_108_male-rider-riding-hats-ventilated-riding-hats"},
{"link": "https://www.thesaddleryshop.co.uk/sc_318_male-rider-riding-hats-riding-hat-covers"},
{"link": "https://www.thesaddleryshop.co.uk/sc_109_male-rider-riding-hats-accessories"},
{"link": "https://www.thesaddleryshop.co.uk/#level31109"},
{"link": "https://www.thesaddleryshop.co.uk/c_1109_male-rider-chaps-gaiters"},
{"link": "https://www.thesaddleryshop.co.uk/sc_112_male-rider-chaps-gaiters-chaps"},
{"link": "https://www.thesaddleryshop.co.uk/sc_114_male-rider-chaps-gaiters-gaiters"},
{"link": "https://www.thesaddleryshop.co.uk/sc_115_male-rider-chaps-gaiters-overtrousers"},
{"link": "https://www.thesaddleryshop.co.uk/#level31108"},
{"link": "https://www.thesaddleryshop.co.uk/c_1108_male-rider-body-protectors"},
{"link": "https://www.thesaddleryshop.co.uk/sc_296_male-rider-body-protectors-all"},
{"link": "https://www.thesaddleryshop.co.uk/#level31112"},
{"link": "https://www.thesaddleryshop.co.uk/c_1112_male-rider-spurs"},
{"link": "https://www.thesaddleryshop.co.uk/sc_1333_male-rider-blunt-end-spurs"},
{"link": "https://www.thesaddleryshop.co.uk/sc_1335_male-rider-ball-end-spurs"},
{"link": "https://www.thesaddleryshop.co.uk/sc_1336_male-rider-spur-straps"},
{"link": "https://www.thesaddleryshop.co.uk/sc_123_male-rider-spurs-all"},
{"link": "https://www.thesaddleryshop.co.uk/#level31113"},
{"link": "https://www.thesaddleryshop.co.uk/c_1113_male-rider-competition-wear"},
{"link": "https://www.thesaddleryshop.co.uk/sc_126_male-rider-competition-wear-mens-competition-jackets"},
{"link": "https://www.thesaddleryshop.co.uk/sc_1338_male-rider-hacking-jackets"},
{"link": "https://www.thesaddleryshop.co.uk/sc_131_male-rider-competition-wear-mens-riding-shirts"},
{"link": "https://www.thesaddleryshop.co.uk/sc_128_male-rider-competition-wear-mens-competition-legwear"},
{"link": "https://www.thesaddleryshop.co.uk/sc_130_male-rider-competition-wear-mens-footwear-gaiters"},
{"link": "https://www.thesaddleryshop.co.uk/sc_134_male-rider-competition-wear-mens-riding-gloves"},
{"link": "https://www.thesaddleryshop.co.uk/sc_124_male-rider-competition-wear-mens-riding-hats"},
{"link": "https://www.thesaddleryshop.co.uk/sc_132_male-rider-competition-wear-mens-competition-acessories"},
{"link": "https://www.thesaddleryshop.co.uk/sc_301_male-rider-competition-wear-mens-stocks-and-stock-pins"},
{"link": "https://www.thesaddleryshop.co.uk/#level31114"},
{"link": "https://www.thesaddleryshop.co.uk/c_1114_male-rider-accessories"},
{"link": "https://www.thesaddleryshop.co.uk/sc_304_male-rider-accessories-all"},
{"link": "https://www.thesaddleryshop.co.uk/#level31176"},
{"link": "https://www.thesaddleryshop.co.uk/c_1176_male-rider-gifts-for-male-riders"},
{"link": "https://www.thesaddleryshop.co.uk/sc_334_male-rider-gifts-for-male-riders-all"},
{"link": "https://www.thesaddleryshop.co.uk/#level31309"},
{"link": "https://www.thesaddleryshop.co.uk/c_1309_cleaning-reproofing-products"},
{"link": "https://www.thesaddleryshop.co.uk/sc_1310_cleaning-reproofing-products"},
{"link": "https://www.thesaddleryshop.co.uk/#level31232"},
{"link": "https://www.thesaddleryshop.co.uk/c_1232_riding-whips-and-crops"},
{"link": "https://www.thesaddleryshop.co.uk/sc_1233_riding-whips-and-riding-crops"},
{"link": "https://www.thesaddleryshop.co.uk/sc_1234_dressage-and-schooling-whips"},
{"link": "https://www.thesaddleryshop.co.uk/sc_1241_hunting-crops-thongs"},
{"link": "https://www.thesaddleryshop.co.uk/#level3-5"},
{"link": "https://www.thesaddleryshop.co.uk/mens-riding-clothing-size-guides"},
{"link": "https://www.thesaddleryshop.co.uk/tuffa-boots-size"},
{"link": "https://www.thesaddleryshop.co.uk/tuffa-chaps-chart-qa"},
{"link": "https://www.thesaddleryshop.co.uk/#level14"},
{"link": "https://www.thesaddleryshop.co.uk/#level31190"},
{"link": "https://www.thesaddleryshop.co.uk/c_1190_lady-rider-clearance-riding-clothing"},
{"link": "https://www.thesaddleryshop.co.uk/sc_364_lady-rider-clearance-riding-clothing-all"},
{"link": "https://www.thesaddleryshop.co.uk/#level31030"},
{"link": "https://www.thesaddleryshop.co.uk/c_1030_clothing-jodhpurs"},
{"link": "https://www.thesaddleryshop.co.uk/sc_1315_riding-tights"},
{"link": "https://www.thesaddleryshop.co.uk/sc_38_lady-rider-jodhpurs-breeches-jodhpurs"},
{"link": "https://www.thesaddleryshop.co.uk/sc_39_lady-rider-jodhpurs-breeches-breeches"},
{"link": "https://www.thesaddleryshop.co.uk/sc_51_lady-rider-jodhpurs-breeches-over-trousers-and-other-riding-legwear"},
{"link": "https://www.thesaddleryshop.co.uk/#level31065"},
{"link": "https://www.thesaddleryshop.co.uk/c_1065_lady-rider-casual-riding-clothing"},
{"link": "https://www.thesaddleryshop.co.uk/sc_70_lady-rider-riding-clothing-riding-gloves"},
{"link": "https://www.thesaddleryshop.co.uk/sc_72_lady-rider-casual-riding-clothing-socks"},
{"link": "https://www.thesaddleryshop.co.uk/sc_73_lady-rider-casual-riding-clothing-caps-hats"},
{"link": "https://www.thesaddleryshop.co.uk/sc_136_lady-rider-casual-riding-clothing-high-visibility"},
{"link": "https://www.thesaddleryshop.co.uk/sc_1314_ladies-base-layers-underwear"},
{"link": "https://www.thesaddleryshop.co.uk/sc_341_lady-rider-casual-riding-clothing-ladies-casual-shirts-riding-tops"},
{"link": "https://www.thesaddleryshop.co.uk/sc_71_lady-rider-casual-riding-clothing-fleece-jackets-jumpers"},
{"link": "https://www.thesaddleryshop.co.uk/sc_344_lady-rider-casual-riding-clothing-ladies-waistcoats-gilets"},
{"link": "https://www.thesaddleryshop.co.uk/sc_98_lady-rider-casual-riding-clothing-riding-jackets"},
{"link": "https://www.thesaddleryshop.co.uk/#level31072"},
{"link": "https://www.thesaddleryshop.co.uk/c_1072_lady-rider-footwear"},
{"link": "https://www.thesaddleryshop.co.uk/sc_1260_country-boots"},
{"link": "https://www.thesaddleryshop.co.uk/sc_1343_ladies-fashion-footwear"},
{"link": "https://www.thesaddleryshop.co.uk/sc_40_lady-rider-footwear-ladies-long-leather-riding-boots"},
{"link": "https://www.thesaddleryshop.co.uk/sc_41_lady-rider-footwear-ladies-long-synthetic-riding-boots"},
{"link": "https://www.thesaddleryshop.co.uk/sc_42_lady-rider-footwear-ladies-jodhpur-boots"},
{"link": "https://www.thesaddleryshop.co.uk/sc_43_lady-rider-footwear-ladies-short-yard-boots"},
{"link": "https://www.thesaddleryshop.co.uk/sc_44_lady-rider-footwear-ladies-long-yard-boots"},
{"link": "https://www.thesaddleryshop.co.uk/sc_45_lady-rider-footwear-ladies-wellington-boots"},
{"link": "https://www.thesaddleryshop.co.uk/sc_46_lady-rider-footwear-ladies-footwear-accessories"},
{"link": "https://www.thesaddleryshop.co.uk/sc_298_lady-rider-footwear-ladies-riding-socks"},
{"link": "https://www.thesaddleryshop.co.uk/#level31036"},
{"link": "https://www.thesaddleryshop.co.uk/c_1036_rider-riding-hat"},
{"link": "https://www.thesaddleryshop.co.uk/sc_316_lady-rider-riding-hats-riding-hat-covers"},
{"link": "https://www.thesaddleryshop.co.uk/sc_64_lady-rider-riding-hats-peaked-riding-hats"},
{"link": "https://www.thesaddleryshop.co.uk/sc_66_lady-rider-riding-hats-accessories-skull-caps"},
{"link": "https://www.thesaddleryshop.co.uk/sc_69_lady-rider-riding-hats-accessories-accessories"},
{"link": "https://www.thesaddleryshop.co.uk/#level31063"},
{"link": "https://www.thesaddleryshop.co.uk/c_1063_lady-rider-chaps-gaiters"},
{"link": "https://www.thesaddleryshop.co.uk/sc_74_lady-rider-chaps-gaiters-chaps"},
{"link": "https://www.thesaddleryshop.co.uk/sc_75_lady-rider-chaps-gaiters-gaiters"},
{"link": "https://www.thesaddleryshop.co.uk/sc_77_lady-rider-chaps-gaiters-overtrousers"},
{"link": "https://www.thesaddleryshop.co.uk/#level31062"},
{"link": "https://www.thesaddleryshop.co.uk/c_1062_lady-rider-body-protectors"},
{"link": "https://www.thesaddleryshop.co.uk/sc_295_lady-rider-body-protectors-all"},
{"link": "https://www.thesaddleryshop.co.uk/#level31069"},
{"link": "https://www.thesaddleryshop.co.uk/c_1069_lady-rider-spurs"},
{"link": "https://www.thesaddleryshop.co.uk/sc_80_lady-rider-spurs-blunt-end-spurs"},
{"link": "https://www.thesaddleryshop.co.uk/sc_79_lady-rider-spurs-ball-end-spurs"},
{"link": "https://www.thesaddleryshop.co.uk/sc_78_lady-rider-spurs-spurs-with-rowels"},
{"link": "https://www.thesaddleryshop.co.uk/sc_339_lady-rider-spurs-spur-straps"},
{"link": "https://www.thesaddleryshop.co.uk/sc_398_lady-rider-spurs-other-spurs"},
{"link": "https://www.thesaddleryshop.co.uk/#level31071"},
{"link": "https://www.thesaddleryshop.co.uk/c_1071_lady-rider-competition-wear"},
{"link": "https://www.thesaddleryshop.co.uk/sc_54_lady-rider-competition-wear-ladies-show-jackets"},
{"link": "https://www.thesaddleryshop.co.uk/sc_57_lady-rider-competition-wear-ladies-hacking-jackets"},
{"link": "https://www.thesaddleryshop.co.uk/sc_52_lady-rider-competition-wear-ladies-competition-riding-shirts"},
{"link": "https://www.thesaddleryshop.co.uk/sc_53_lady-rider-competition-wear-ladies-competition-jodhpurs-breeches"},
{"link": "https://www.thesaddleryshop.co.uk/sc_107_lady-rider-competition-wear-ladies-footwear-gaiters"},
{"link": "https://www.thesaddleryshop.co.uk/sc_55_lady-rider-competition-wear-ladies-competion-gloves"},
{"link": "https://www.thesaddleryshop.co.uk/sc_56_lady-rider-competition-wear-ladies-riding-hats"},
{"link": "https://www.thesaddleryshop.co.uk/sc_82_lady-rider-competition-wear-ladies-stocks-stock-pins"},
{"link": "https://www.thesaddleryshop.co.uk/sc_60_lady-rider-competition-wear-ladies-competition-accessories"},
{"link": "https://www.thesaddleryshop.co.uk/#level31105"},
{"link": "https://www.thesaddleryshop.co.uk/c_1105_lady-rider-accessories"},
{"link": "https://www.thesaddleryshop.co.uk/sc_302_lady-rider-accessories-all"},
{"link": "https://www.thesaddleryshop.co.uk/#level31175"},
{"link": "https://www.thesaddleryshop.co.uk/c_1175_lady-rider-gifts-for-the-lady-rider"},
{"link": "https://www.thesaddleryshop.co.uk/sc_1201_equine-jewellery"},
{"link": "https://www.thesaddleryshop.co.uk/sc_333_lady-rider-gifts-for-lady-riders-all"},
{"link": "https://www.thesaddleryshop.co.uk/#level31307"},
{"link": "https://www.thesaddleryshop.co.uk/c_1307_cleaning-reproofing"},
{"link": "https://www.thesaddleryshop.co.uk/sc_1308_cleaning-reproofing-products"},
{"link": "https://www.thesaddleryshop.co.uk/#level31221"},
{"link": "https://www.thesaddleryshop.co.uk/c_1221_riding-whips-and-crops"},
{"link": "https://www.thesaddleryshop.co.uk/sc_1228_riding-whips-and-riding-crops"},
{"link": "https://www.thesaddleryshop.co.uk/sc_1230_dressage-and-schooling-whips"},
{"link": "https://www.thesaddleryshop.co.uk/sc_1240_hunting-crops-thongs"},
{"link": "https://www.thesaddleryshop.co.uk/#level3-4"},
{"link": "https://www.thesaddleryshop.co.uk/womens-riding-clothing-size"},
{"link": "https://www.thesaddleryshop.co.uk/#level18"},
{"link": "https://www.thesaddleryshop.co.uk/#level31219"},
{"link": "https://www.thesaddleryshop.co.uk/c_1219_riding-whips-and-crops"},
{"link": "https://www.thesaddleryshop.co.uk/sc_1226_riding-whips-and-riding-crops"},
{"link": "https://www.thesaddleryshop.co.uk/sc_1225_dressage-and-schooing-whips"},
{"link": "https://www.thesaddleryshop.co.uk/#level31115"},
{"link": "https://www.thesaddleryshop.co.uk/c_1115_young-rider-riding-hats-accessories"},
{"link": "https://www.thesaddleryshop.co.uk/sc_317_young-rider-riding-hats-riding-hat-covers"},
{"link": "https://www.thesaddleryshop.co.uk/sc_88_young-rider-riding-hats-peaked-riding-hats"},
{"link": "https://www.thesaddleryshop.co.uk/sc_89_young-rider-riding-hats-skull-caps"},
{"link": "https://www.thesaddleryshop.co.uk/sc_90_young-rider-riding-hats-accessories"},
{"link": "https://www.thesaddleryshop.co.uk/#level31116"},
{"link": "https://www.thesaddleryshop.co.uk/c_1116_young-rider-jodhpurs"},
{"link": "https://www.thesaddleryshop.co.uk/sc_91_young-rider-jodhpurs-all"},
{"link": "https://www.thesaddleryshop.co.uk/#level31117"},
{"link": "https://www.thesaddleryshop.co.uk/c_1117_young-rider-body-protectors"},
{"link": "https://www.thesaddleryshop.co.uk/sc_294_young-rider-body-protectors-all"},
{"link": "https://www.thesaddleryshop.co.uk/#level31118"},
{"link": "https://www.thesaddleryshop.co.uk/c_1118_young-rider-half-chaps-gaiters"},
{"link": "https://www.thesaddleryshop.co.uk/sc_92_young-rider-half-chaps-gaiters-half-chaps"},
{"link": "https://www.thesaddleryshop.co.uk/sc_93_young-rider-half-chaps-gaiters-gaiters"},
{"link": "https://www.thesaddleryshop.co.uk/#level31119"},
{"link": "https://www.thesaddleryshop.co.uk/c_1119_young-rider-footwear"},
{"link": "https://www.thesaddleryshop.co.uk/sc_321_young-rider-footwear-accessories"},
{"link": "https://www.thesaddleryshop.co.uk/sc_94_young-rider-footwear-childrens-yard-boots"},
{"link": "https://www.thesaddleryshop.co.uk/sc_95_young-rider-footwear-childrens-riding-boots"},
{"link": "https://www.thesaddleryshop.co.uk/sc_299_young-rider-footwear-childrens-riding-socks"},
{"link": "https://www.thesaddleryshop.co.uk/#level31120"},
{"link": "https://www.thesaddleryshop.co.uk/c_1120_young-rider-casual-riding-clothing"},
{"link": "https://www.thesaddleryshop.co.uk/sc_342_young-rider-casual-riding-clothing-childrens-casual-shirts-riding-tops"},
{"link": "https://www.thesaddleryshop.co.uk/sc_308_young-rider-casual-riding-clothing-childrens-gilets-waistcoats"},
{"link": "https://www.thesaddleryshop.co.uk/sc_324_young-rider-casual-riding-clothing-childrens-jumpers-fleeces"},
{"link": "https://www.thesaddleryshop.co.uk/sc_96_young-rider-casual-riding-clothing-childrens-riding-gloves"},
{"link": "https://www.thesaddleryshop.co.uk/sc_97_young-rider-casual-riding-clothing-childrens-riding-jackets"},
{"link": "https://www.thesaddleryshop.co.uk/sc_99_young-rider-casual-riding-clothing-childrens-riding-socks"},
{"link": "https://www.thesaddleryshop.co.uk/sc_138_young-rider-casual-riding-clothing-high-visibility"},
{"link": "https://www.thesaddleryshop.co.uk/#level31121"},
{"link": "https://www.thesaddleryshop.co.uk/c_1121_young-rider-competition-wear"},
{"link": "https://www.thesaddleryshop.co.uk/sc_331_young-rider-competition-wear-stocks-and-stock-pins"},
{"link": "https://www.thesaddleryshop.co.uk/sc_135_young-rider-competition-wear-gloves"},
{"link": "https://www.thesaddleryshop.co.uk/sc_100_young-rider-competition-wear-riding-hats"},
{"link": "https://www.thesaddleryshop.co.uk/sc_101_young-rider-competition-wear-competition-jackets"},
{"link": "https://www.thesaddleryshop.co.uk/sc_102_young-rider-competition-wear-competition-jodhpurs"},
{"link": "https://www.thesaddleryshop.co.uk/sc_103_young-rider-competition-wear-footwear-gaiters"},
{"link": "https://www.thesaddleryshop.co.uk/sc_104_young-rider-competition-wear-competition-accessories"},
{"link": "https://www.thesaddleryshop.co.uk/sc_105_young-rider-competition-wear-show-shirts"},
{"link": "https://www.thesaddleryshop.co.uk/#level31174"},
{"link": "https://www.thesaddleryshop.co.uk/c_1174_young-rider-spurs"},
{"link": "https://www.thesaddleryshop.co.uk/sc_328_young-rider-spurs-all"},
{"link": "https://www.thesaddleryshop.co.uk/#level31122"},
{"link": "https://www.thesaddleryshop.co.uk/c_1122_young-rider-accessories"},
{"link": "https://www.thesaddleryshop.co.uk/sc_305_young-rider-accessories-all"},
{"link": "https://www.thesaddleryshop.co.uk/#level31178"},
{"link": "https://www.thesaddleryshop.co.uk/c_1178_young-rider-gifts-for-the-young-rider"},
{"link": "https://www.thesaddleryshop.co.uk/sc_335_young-rider-gifts-for-the-young-rider-all"},
{"link": "https://www.thesaddleryshop.co.uk/#level31192"},
{"link": "https://www.thesaddleryshop.co.uk/c_1192_young-rider-childrens-clearence-riding-wear"},
{"link": "https://www.thesaddleryshop.co.uk/sc_367_young-rider-childrens-clearence-riding-wear-all"},
{"link": "https://www.thesaddleryshop.co.uk/#level31311"},
{"link": "https://www.thesaddleryshop.co.uk/c_1311_cleaning-reproofing-products"},
{"link": "https://www.thesaddleryshop.co.uk/sc_1312_cleaning-reproofing-products"},
{"link": "https://www.thesaddleryshop.co.uk/#level3-8"},
{"link": "https://www.thesaddleryshop.co.uk/childrens-riding-clothing-size-guide"},
{"link": "https://www.thesaddleryshop.co.uk/#level11275"},
{"link": "https://www.thesaddleryshop.co.uk/#level31278"},
{"link": "https://www.thesaddleryshop.co.uk/c_1278_chicken-and-poultry-feed-and-toys"},
{"link": "https://www.thesaddleryshop.co.uk/sc_1283_hen-acessories-and-treats"},
{"link": "https://www.thesaddleryshop.co.uk/#level31279"},
{"link": "https://www.thesaddleryshop.co.uk/c_1279_dog-coats-and-toys"},
{"link": "https://www.thesaddleryshop.co.uk/sc_1280_dog-coats-and-dog-rugs"},
{"link": "https://www.thesaddleryshop.co.uk/sc_1282_dog-toys"},
{"link": "https://www.thesaddleryshop.co.uk/sc_1284_dog-accessories-treats"},
{"link": "https://www.thesaddleryshop.co.uk/sc_1295_dog-collars-and-leads"},
{"link": "https://www.thesaddleryshop.co.uk/sc_1298_dog-beds"},
{"link": "https://www.thesaddleryshop.co.uk/sc_1318_dog-treats-feeding"},
{"link": "https://www.thesaddleryshop.co.uk/sc_1319_dog-grooming"},
{"link": "https://www.thesaddleryshop.co.uk/sc_1320_dog-health-care"},
{"link": "https://www.thesaddleryshop.co.uk/sc_1347_dog-sale-and-clearance"},
{"link": "https://www.thesaddleryshop.co.uk/#level11299"},
{"link": "https://www.thesaddleryshop.co.uk/#level31303"},
{"link": "https://www.thesaddleryshop.co.uk/c_1303_stocking-filler"},
{"link": "https://www.thesaddleryshop.co.uk/sc_1300_stocking-fillers-5-and-under"},
{"link": "https://www.thesaddleryshop.co.uk/sc_1301_stocking-fillers-10-and-under"},
{"link": "https://www.thesaddleryshop.co.uk/sc_1302_stocking-fillers-20-and-under"},
{"link": "https://www.thesaddleryshop.co.uk/#level3-2598"},
{"link": "https://www.thesaddleryshop.co.uk/sc_1176_male-rider-gifts-for-male-riders"},
{"link": "https://www.thesaddleryshop.co.uk/sc_1178_young-rider-gifts-for-the-young-rider"},
{"link": "https://www.thesaddleryshop.co.uk/search?kws=vouchers"},
{"link": "https://www.thesaddleryshop.co.uk/equestrian-clearance"},
{"link": "https://www.thesaddleryshop.co.uk/Guides-Rugs/Autumn-Rugs"},
{"link": "https://www.thesaddleryshop.co.uk/d_4_lady-rider#!/filter=true&cats=1030,&brands=217,&psize=36"},
{"link": "https://www.thesaddleryshop.co.uk/p_22348_easyboot-sneaker-hoof-boot"},
{"link": "https://www.thesaddleryshop.co.uk/Guides/Intro"},
{"link": "https://www.facebook.com/TheSaddleryShop"},
{"link": "https://twitter.com/TheSaddleryShop"},
{"link": "https://instagram.com/TheSaddleryShop"},
{"link": "https://www.thesaddleryshop.co.uk/cookie-policy"},
{"link": "https://www.thesaddleryshop.co.uk/privacy-policy"},
{"link": "https://www.thesaddleryshop.co.uk/terms"},
{"link": "http://www.eventureinternet.com/"}
]